LICENSE
MANIFEST.in
README.rst
VERSION
requirements.txt
setup.cfg
setup.py
rhasspy_hermes.egg-info/PKG-INFO
rhasspy_hermes.egg-info/SOURCES.txt
rhasspy_hermes.egg-info/dependency_links.txt
rhasspy_hermes.egg-info/requires.txt
rhasspy_hermes.egg-info/top_level.txt
rhasspyhermes/__init__.py
rhasspyhermes/__main__.py
rhasspyhermes/asr.py
rhasspyhermes/audioserver.py
rhasspyhermes/base.py
rhasspyhermes/cli.py
rhasspyhermes/client.py
rhasspyhermes/dialogue.py
rhasspyhermes/g2p.py
rhasspyhermes/handle.py
rhasspyhermes/intent.py
rhasspyhermes/nlu.py
rhasspyhermes/py.typed
rhasspyhermes/train.py
rhasspyhermes/tts.py
rhasspyhermes/utils.py
rhasspyhermes/wake.py
tests/__init__.py
tests/test_asr.py
tests/test_audio_server.py
tests/test_dialogue.py
tests/test_handle.py
tests/test_nlu.py
tests/test_tts.py
tests/test_wake.py